hsr_pic_parser/__init__.py
hsr_pic_parser/character_picture.py
hsr_pic_parser/cut_url.py
hsr_pic_parser/get_cone.py
hsr_pic_parser/get_picture_info.py
hsr_pic_parser/get_relic.py
hsr_pic_parser/picture_url.py
hsr_pic_parser/prydwen.py
hsr_pic_parcer-1.0.3.dist-info/LICENCE.txt
hsr_pic_parcer-1.0.3.dist-info/METADATA
hsr_pic_parcer-1.0.3.dist-info/WHEEL
hsr_pic_parcer-1.0.3.dist-info/top_level.txt
hsr_pic_parcer-1.0.3.dist-info/RECORD
