Metadata-Version: 2.1
Name: hsr_pic_parcer
Version: 1.0.3
Summary: parser to get images from hsr mana
Home-page: https://github.com/vano979797/hsr_pic_parser
Author: vano979797
Author-email: vano979797@gmail.com
Project-URL: Documentation, https://github.com/vano979797/hsr_pic_parser/blob/4a0309d617f93c56714fe206753119f690109219/README.md
Keywords: python parse hsr
Classifier: Programming Language :: Python :: 3.12
Classifier: License :: OSI Approved :: MIT License
Classifier: Operating System :: OS Independent
Requires-Python: >=3.7
License-File: LICENCE.txt
Requires-Dist: requests >=2.25.1
Requires-Dist: beautifulsoup4 >=4.12.3
